LICENSE
README.md
pyproject.toml
setup.py
mml_qae/Chinese_dealing.py
mml_qae/MoreErrors.py
mml_qae/__init__.py
mml_qae/easy_web.py
mml_qae/lists_of_number.py
mml_qae/one_list_of_number.py
mml_qae.egg-info/PKG-INFO
mml_qae.egg-info/SOURCES.txt
mml_qae.egg-info/dependency_links.txt
mml_qae.egg-info/top_level.txt