Metadata-Version: 2.1
Name: mml-qae
Version: 1.0.3.1
Summary: The packages for the machine learning(just easily learn!) are always hard to study, and difficult to use. Now you have the MyMachineLearning_Quicker_and_Easier! It can maybe help you to use machine learning.
Home-page: https://www.python.org
Author: ETRO_secondleader
Author-email: ETRO_secondleader <ETRO_gfyx@163.com>
Project-URL: Homepage, https://github.com/pypa/mml_qae
Project-URL: Author's Git, https://github.com/ZYpS-leader?tab=repositories
Classifier: Programming Language :: Python :: 3
Classifier: License :: OSI Approved :: MIT License
Classifier: Operating System :: OS Independent
Requires-Python: ==3.7.2
License-File: LICENSE
